danmu/Abstract.py
danmu/Bilibili.py
danmu/DouYu.py
danmu/HuoMao.py
danmu/Panda.py
danmu/QuanMin.py
danmu/ZhanQi.py
danmu/__init__.py
danmu/config.py
danmu/log.py
danmu-1.0.5.dist-info/DESCRIPTION.rst
danmu-1.0.5.dist-info/METADATA
danmu-1.0.5.dist-info/RECORD
danmu-1.0.5.dist-info/WHEEL
danmu-1.0.5.dist-info/metadata.json
danmu-1.0.5.dist-info/top_level.txt
