Metadata-Version: 2.0
Name: danmu
Version: 1.0.5
Summary: A live danmu package
Home-page: https://github.com/littlecodersh/danmu
Author: LittleCoder
Author-email: i7meavnktqegm1b@qq.com
License: MIT
Keywords: danmu douyu panda zhanqi quanmin
Platform: UNKNOWN
Classifier: Development Status :: 3 - Alpha
Classifier: Intended Audience :: Developers
Classifier: Topic :: Software Development :: Libraries :: Python Modules
Classifier: License :: OSI Approved :: MIT License
Classifier: Programming Language :: Python :: 2.7
Classifier: Programming Language :: Python :: 3.5
Requires-Dist: requests
